polars_ml-0.2.0.dist-info/METADATA
polars_ml-0.2.0.dist-info/WHEEL
polars_ml-0.2.0.dist-info/licenses/LICENSE.txt
polars_ml/graph/node2vec_function.py
polars_ml/graph/graph_namespace.py
polars_ml/graph/functions.py
polars_ml/graph/__init__.py
polars_ml/nltk/functions.py
polars_ml/nltk/__init__.py
polars_ml/nltk/nltk_namespace.py
polars_ml/sparse/sparse_namespace.py
polars_ml/sparse/constants.py
polars_ml/sparse/functions.py
polars_ml/sparse/__init__.py
polars_ml/__init__.py
polars_ml/polars_ml.abi3.so
polars_ml-0.2.0.dist-info/RECORD
