Metadata-Version: 2.3
Name: polars_ml
Version: 0.2.0
Classifier: Programming Language :: Rust
Classifier: Programming Language :: Python :: Implementation :: CPython
Classifier: Programming Language :: Python :: Implementation :: PyPy
Requires-Dist: polars >=0.20.19
License-File: LICENSE.txt
Requires-Python: >=3.8
